tinybpe/__init__.py
tinybpe/_utils.py
tinybpe/bpe.cp313t-win_amd64.pyd
tinybpe/bpe.pyi
tinybpe/core.py
tinybpe/simple.py
tinybpe-0.1.1.dist-info/licenses/LICENSE
tinybpe-0.1.1.dist-info/METADATA
tinybpe-0.1.1.dist-info/WHEEL
tinybpe-0.1.1.dist-info/top_level.txt
tinybpe-0.1.1.dist-info/RECORD
