Metadata-Version: 2.4
Name: tinybpe
Version: 0.1.1
Summary: This is an ultra-fast, lightweight and clean code implementation of the Byte Pair Encoding (BPE) algorithm.
Author-email: "E.T. Romani" <myneluca@gmail.com>
License: MIT License
Project-URL: Homepage, https://github.com/neluca/tinybpe
Keywords: BPE,Byte Pair Encoding,LLM,Tokenizer
Classifier: Development Status :: 5 - Production/Stable
Classifier: Programming Language :: Python :: 3.9
Classifier: Programming Language :: Python :: 3.10
Classifier: Programming Language :: Python :: 3.11
Classifier: Programming Language :: Python :: 3.12
Classifier: Programming Language :: Python :: 3.13
Classifier: Intended Audience :: Developers
Classifier: Intended Audience :: Science/Research
Classifier: Operating System :: MacOS
Classifier: Operating System :: POSIX :: Linux
Classifier: Operating System :: Microsoft :: Windows
Classifier: Topic :: Text Processing :: Linguistic
Classifier: Topic :: Software Development :: Libraries :: Python Modules
Requires-Python: >=3.9
License-File: LICENSE
Requires-Dist: regex
Dynamic: license-file
